uselesss/__init__.py
uselesss/cli.py
uselesss/run.py
uselesss/src/__init__.py
uselesss/src/deduplicate.py
uselesss/src/dir_combine.py
uselesss/src/label_combine.py
uselesss/src/labelling_cls.py
uselesss/src/labelling_det.py
uselesss/src/spider.py
uselesss/src/utils.py
uselesss/src/video_tools.py
uselesss-0.0.2.dist-info/METADATA
uselesss-0.0.2.dist-info/WHEEL
uselesss-0.0.2.dist-info/entry_points.txt
uselesss-0.0.2.dist-info/top_level.txt
uselesss-0.0.2.dist-info/RECORD
