Metadata-Version: 2.1
Name: uselesss
Version: 0.0.2
Summary: Useless CV toolkits
Author: jamjamjon
Requires-Python: >=3.7
Requires-Dist: antlr4-python3-runtime (==4.9.3)
Requires-Dist: BaiduSpider (==1.0.2.6)
Requires-Dist: beautifulsoup4 (==4.11.2)
Requires-Dist: bs4 (==0.0.1)
Requires-Dist: certifi (==2022.12.7)
Requires-Dist: charset-normalizer (==3.0.1)
Requires-Dist: hydra-core (==1.3.1)
Requires-Dist: idna (==3.4)
Requires-Dist: loguru (==0.6.0)
Requires-Dist: markdown-it-py (==2.1.0)
Requires-Dist: mdurl (==0.1.2)
Requires-Dist: numpy (==1.24.2)
Requires-Dist: omegaconf (==2.3.0)
Requires-Dist: opencv-python (==4.7.0.68)
Requires-Dist: packaging (==23.0)
Requires-Dist: Pillow (==9.4.0)
Requires-Dist: psutil (==5.9.4)
Requires-Dist: Pygments (==2.14.0)
Requires-Dist: pynvml (==11.5.0)
Requires-Dist: PyYAML (==6.0)
Requires-Dist: requests (==2.28.2)
Requires-Dist: rich (==13.3.1)
Requires-Dist: soupsieve (==2.4)
Requires-Dist: tqdm (==4.64.1)
Requires-Dist: urllib3 (==1.26.14)
